sgpv/__init__.py
sgpv/data.py
sgpv/leukstats.csv
sgpv/sgpv.py
sgpv/sgpv_test.py
sgpv-1.0.3.post1.dist-info/LICENSE
sgpv-1.0.3.post1.dist-info/METADATA
sgpv-1.0.3.post1.dist-info/WHEEL
sgpv-1.0.3.post1.dist-info/top_level.txt
sgpv-1.0.3.post1.dist-info/RECORD
