Metadata-Version: 2.1
Name: sgpv
Version: 1.0.3.post1
Summary: Tools to calculate SGPVs
Home-page: https://github.com/skbormann/python-tools/sgpv
Author: Sven-Kristjan Bormann
Author-email: sven-kristjan@gmx.de
License: UNKNOWN
Keywords: "second generation p-values" sgpv "false discovery risk"         "false confirmatory risk" power-function
Platform: UNKNOWN
Classifier: Programming Language :: Python :: 3
Classifier: License :: OSI Approved :: MIT License
Classifier: Operating System :: OS Independent
Requires-Python: >=3.7
Requires-Dist: pandas (>=1.0.4)
Requires-Dist: matplotlib (>=3.2.1)
Requires-Dist: numpy (>=1.18.0)
Requires-Dist: scipy (>=1.3.2)
